pynlptool/__init__.py
pynlptool/cli.py
pynlptool/data_utils.py
pynlptool/evaluate.py
pynlptool/model.pkl
pynlptool/model.py
pynlptool/py.typed
pynlptool-0.1.0.dist-info/licenses/LICENSE
pynlptool-0.1.0.dist-info/METADATA
pynlptool-0.1.0.dist-info/WHEEL
pynlptool-0.1.0.dist-info/entry_points.txt
pynlptool-0.1.0.dist-info/top_level.txt
pynlptool-0.1.0.dist-info/RECORD
