Metadata-Version: 2.4
Name: pynlptool
Version: 0.1.0
Summary: 基于隐马尔可夫模型(HMM)的中文分词和序列标注工具库
Author-email: Luck_mx <muxinglucky@gmail.com>
License: MIT
Project-URL: Homepage, https://github.com/li-k-z/pynlptool
Project-URL: Repository, https://github.com/li-k-z/pynlptool
Project-URL: Documentation, https://github.com/li-k-z/pynlptool#readme
Project-URL: Issues, https://github.com/li-k-z/pynlptool/issues
Keywords: chinese,segmentation,nlp,hmm,hidden-markov-model,sequence-labeling,tokenization
Classifier: Development Status :: 4 - Beta
Classifier: Intended Audience :: Developers
Classifier: Intended Audience :: Science/Research
Classifier: License :: OSI Approved :: MIT License
Classifier: Operating System :: OS Independent
Classifier: Programming Language :: Python :: 3
Classifier: Programming Language :: Python :: 3.8
Classifier: Programming Language :: Python :: 3.9
Classifier: Programming Language :: Python :: 3.10
Classifier: Programming Language :: Python :: 3.11
Classifier: Programming Language :: Python :: 3.12
Classifier: Topic :: Scientific/Engineering :: Artificial Intelligence
Classifier: Topic :: Text Processing :: Linguistic
Requires-Python: >=3.8
License-File: LICENSE
Provides-Extra: dev
Requires-Dist: pytest>=7.0; extra == "dev"
Requires-Dist: pytest-cov>=4.0; extra == "dev"
Requires-Dist: black>=23.0; extra == "dev"
Requires-Dist: isort>=5.0; extra == "dev"
Requires-Dist: mypy>=1.0; extra == "dev"
Dynamic: license-file
